pycli/__init__.py
pycli/core.py
pycli/default_handlers.py
pycli/exceptions.py
pycli/ext/audio/__init__.py
pycli/ext/audio/output/__init__.py
pycli/utils/__init__.py
pycli/utils/load_extension.py
pycli/utils/transformer.py
pycli/utils/utils.py
skycli.py-0.0.1.dist-info/LICENCE
skycli.py-0.0.1.dist-info/METADATA
skycli.py-0.0.1.dist-info/WHEEL
skycli.py-0.0.1.dist-info/top_level.txt
skycli.py-0.0.1.dist-info/RECORD
