Metadata-Version: 2.1
Name: skycli.py
Version: 0.0.1
Summary: A CLI package which attempts to mimic the style of discord.py
Author-email: SkyTheCodeMaster <sky@skystuff.cc>
Project-URL: Homepage, https://github.com/skythecodemaster/pycli-lib/
Project-URL: Issues, https://github.com/skythecodemaster/pycli-lib/issues
Classifier: Programming Language :: Python :: 3
Classifier: License :: OSI Approved :: MIT License
Classifier: Operating System :: OS Independent
Requires-Python: >=3.8
License-File: LICENCE
Requires-Dist: aioconsole ==0.7.0
Requires-Dist: pyttsx3 ==2.71
